pipeline_ALU.v
module pipeline_ALU(Zout,rs1,rs2,rd,func,addr,clk1,clk2);
  input [3:0] rs1,rs2,rd,func;
  input [7:0] addr;
  input clk1,clk2;      // TWo phase clock
  output [15:0] Zout;
  
  reg[15:0] L12_A,L12_B,L23_Z,L34_Z;
  reg[3:0] L12_rd,L12_func,L23_rd;
  reg[7:0] L12_addr,L23_addr,L34_addr;
  
  reg [15:0] Reg_Bank [0:15];   //Register Bank
  reg [15:0] mem [0:255];   //256x16 Memory
  
  assign Zout=L34_Z;
  
  always @(posedge clk1)  // STAGE 1
    begin 
      L12_A <= #2 Reg_Bank[rs1];
      L12_B <= #2 Reg_Bank[rs2];
      L12_rd <= #2 rd;
      L12_func <= #2 func;
      L12_addr <= #2 addr;
     end
  
  always @(negedge clk2)  // STAGE 2
    begin 
      case(func)
        0: L23_Z <= #2 L12_A + L12_B;
        1: L23_Z <= #2 L12_A - L12_B;
        2: L23_Z <= #2 L12_A * L12_B;
        3: L23_Z <= #2 L12_A;
        4: L23_Z <= #2 L12_B;
        5: L23_Z <= #2 L12_A & L12_B;
        6: L23_Z <= #2 L12_A | L12_B;
        7: L23_Z <= #2 L12_A ^ L12_B;
        8: L23_Z <= #2 -L12_A; 
        9: L23_Z <= #2 -L12_A;
        10: L23_Z <= #2 L12_A>>1;
        11: L23_Z <= #2 L12_A<<1;
        default : L23_Z<= #2 16'hxxxx;
      endcase
      L23_rd <= #2 L12_rd;
      L23_addr <= #2 L12_addr;
    end
      
  always@(posedge clk1)  // STAGE 3
    begin 
      Reg_Bank[L23_rd] <= #2 L23_Z;
      L34_Z <= #2 L23_Z;
      L34_addr <= #2 L23_addr;
    end
  
  always @(negedge clk2) // STAGE 4
    begin 
      mem[L34_addr]<= #2 L34_Z;
    end
endmodule

pipeline_test.v
module pipeline_test;
  
  wire [15:0] Zout;
  reg [3:0]rs1,rs2,rd,func;
  reg [7:0]addr;
  reg clk1,clk2;
  integer k;
    
    
  pipeline_ALU PIPE (Zout,rs1,rs2,rd,func,addr,clk1,clk2);
    
    initial 
      begin 
        clk1=0; clk2=0;  // Generating Two Phase Clock
        repeat(20)
          begin 
            #5 clk1=1; #5 clk1=0;
            #5 clk2=1; #5 clk2=0;
          end
      end
    
    initial 
      for(k=0; k<16; k++)
        PIPE.Reg_Bank[k] =k;   // Initialize Registers
    
    initial 
      begin 
         #5 rs1=3; rs2=5; rd=10; func=0; addr=125;   //ADD
         #20 rs1=3; rs2=8; rd=12; func=2; addr=126;   //MUL
         #20 rs1=10; rs2=5; rd=14; func=1; addr=128;   //SUB
         #20 rs1=7; rs2=3; rd=13; func=11; addr=127;   //SLA
         #20 rs1=10; rs2=5; rd=15; func=1; addr=129;   //SUB
         #20 rs1=12; rs2=13; rd=16; func=0; addr=130;   //ADD
     
        #60 for(k=125 ; k<131 ;k++)
          $display ("Mem[%3d] =%3d" ,k,PIPE.mem[k]);
      end
    initial 
      begin 
        $dumpfile("pipe.vcd");
        $dumpvars(0,pipeline_test);
        $monitor("Time: %3d, F= %3d" , $time,Zout);
          #300 $finish;
      end
endmodule

pipe.vcd
$date
	Wed Sep 04 13:33:22 2024
$end
$version
	Icarus Verilog
$end
$timescale
	1s
$end
$scope module pipeline_test $end
$var wire 16 ! Zout [15:0] $end
$var reg 8 " addr [7:0] $end
$var reg 1 # clk1 $end
$var reg 1 $ clk2 $end
$var reg 4 % func [3:0] $end
$var reg 4 & rd [3:0] $end
$var reg 4 ' rs1 [3:0] $end
$var reg 4 ( rs2 [3:0] $end
$var integer 32 ) k [31:0] $end
$scope module PIPE $end
$var wire 16 * Zout [15:0] $end
$var wire 8 + addr [7:0] $end
$var wire 1 # clk1 $end
$var wire 1 $ clk2 $end
$var wire 4 , func [3:0] $end
$var wire 4 - rd [3:0] $end
$var wire 4 . rs1 [3:0] $end
$var wire 4 / rs2 [3:0] $end
$var reg 16 0 L12_A [15:0] $end
$var reg 16 1 L12_B [15:0] $end
$var reg 8 2 L12_addr [7:0] $end
$var reg 4 3 L12_func [3:0] $end
$var reg 4 4 L12_rd [3:0] $end
$var reg 16 5 L23_Z [15:0] $end
$var reg 8 6 L23_addr [7:0] $end
$var reg 4 7 L23_rd [3:0] $end
$var reg 16 8 L34_Z [15:0] $end
$var reg 8 9 L34_addr [7:0] $end
$upscope $end
$upscope $end
$enddefinitions $end
$comment Show the parameter values. $end
$dumpall
$end
#0
$dumpvars
bx 9
bx 8
bx 7
bx 6
bx 5
bx 4
bx 3
bx 2
bx 1
bx 0
bx /
bx .
bx -
bx ,
bx +
bx *
b10000 )
bx (
bx '
bx &
bx %
0$
0#
bx "
bx !
$end
#5
b1111101 "
b1111101 +
b0 %
b0 ,
b1010 &
b1010 -
b101 (
b101 /
b11 '
b11 .
1#
#7
b1111101 2
b0 3
b1010 4
b101 1
b11 0
#10
0#
#15
1$
#20
0$
#22
b1111101 6
b1010 7
b1000 5
#25
1#
b1111110 "
b1111110 +
b10 %
b10 ,
b1100 &
b1100 -
b1000 (
b1000 /
#27
b1111101 9
b1000 !
b1000 *
b1000 8
b1111110 2
b10 3
b1100 4
b1000 1
#30
0#
#35
1$
#40
0$
#42
b1111110 6
b1100 7
b11000 5
#45
1#
b10000000 "
b10000000 +
b1 %
b1 ,
b1110 &
b1110 -
b101 (
b101 /
b1010 '
b1010 .
#47
b10000000 2
b1 3
b1110 4
b101 1
b1000 0
b1111110 9
b11000 !
b11000 *
b11000 8
#50
0#
#55
1$
#60
0$
#62
b10000000 6
b1110 7
b11 5
#65
1#
b1111111 "
b1111111 +
b1011 %
b1011 ,
b1101 &
b1101 -
b11 (
b11 /
b111 '
b111 .
#67
b10000000 9
b11 !
b11 *
b11 8
b1111111 2
b1011 3
b1101 4
b11 1
b111 0
#70
0#
#75
1$
#80
0$
#82
b1111111 6
b1101 7
b1110 5
#85
1#
b10000001 "
b10000001 +
b1 %
b1 ,
b1111 &
b1111 -
b101 (
b101 /
b1010 '
b1010 .
#87
b10000001 2
b1 3
b1111 4
b101 1
b1000 0
b1111111 9
b1110 !
b1110 *
b1110 8
#90
0#
#95
1$
#100
0$
#102
b10000001 6
b1111 7
b11 5
#105
1#
b10000010 "
b10000010 +
b0 %
b0 ,
b0 &
b0 -
b1101 (
b1101 /
b1100 '
b1100 .
#107
b10000001 9
b11 !
b11 *
b11 8
b10000010 2
b0 3
b0 4
b1110 1
b11000 0
#110
0#
#115
1$
#120
0$
#122
b10000010 6
b0 7
b100110 5
#125
1#
#127
b10000010 9
b100110 !
b100110 *
b100110 8
#130
0#
#135
1$
#140
0$
#145
1#
#150
0#
#155
1$
#160
0$
#165
1#
b10000011 )
